lltune/__init__.py
lltune/apply_engine.py
lltune/cli.py
lltune/config_gen.py
lltune/config_model.py
lltune/discovery.py
lltune/env.py
lltune/logging_utils.py
lltune/models.py
lltune/persistence.py
lltune/ptp_config.py
lltune/py.typed
lltune/recommendations.py
lltune/report.py
lltune/shell.py
lltune/user_stack_config.py
lltune/utils.py
lltune/validation_hooks.py
lltune/version.py
lltune/commands/__init__.py
lltune/commands/apply.py
lltune/commands/audit.py
lltune/commands/gen_config.py
lltune/commands/rollback.py
lltune/commands/scan.py
lltune-0.1.1.dist-info/licenses/LICENSE
lltune-0.1.1.dist-info/METADATA
lltune-0.1.1.dist-info/WHEEL
lltune-0.1.1.dist-info/entry_points.txt
lltune-0.1.1.dist-info/top_level.txt
lltune-0.1.1.dist-info/RECORD
