Metadata-Version: 2.4
Name: lltune
Version: 0.1.1
Summary: Low-Latency System Tuner CLI and library
Author-email: Muhammad Nawaz <m.nawaz2003@gmail.com>
License-Expression: MIT
Project-URL: Homepage, https://github.com/nawaz1991/lltune
Project-URL: Repository, https://github.com/nawaz1991/lltune
Project-URL: Documentation, https://github.com/nawaz1991/lltune#readme
Keywords: low-latency,latency,HFT,high-frequency-trading,trading,linux,performance,tuning,optimization,kernel,network,cpu-isolation,irq-affinity,hugepages,numa,real-time,sysctl,server,fintech
Classifier: Development Status :: 4 - Beta
Classifier: Environment :: Console
Classifier: Intended Audience :: Developers
Classifier: Intended Audience :: Financial and Insurance Industry
Classifier: Intended Audience :: System Administrators
Classifier: Operating System :: POSIX :: Linux
Classifier: Programming Language :: Python :: 3
Classifier: Programming Language :: Python :: 3.9
Classifier: Programming Language :: Python :: 3.10
Classifier: Programming Language :: Python :: 3.11
Classifier: Programming Language :: Python :: 3.12
Classifier: Topic :: System :: Systems Administration
Classifier: Topic :: System :: Networking
Classifier: Topic :: System :: Operating System Kernels :: Linux
Classifier: Typing :: Typed
Requires-Python: >=3.9
License-File: LICENSE
Requires-Dist: pyyaml>=6.0
Requires-Dist: ruamel.yaml>=0.17
Provides-Extra: dev
Requires-Dist: pytest>=7; extra == "dev"
Requires-Dist: flake8>=7; extra == "dev"
Requires-Dist: build>=1; extra == "dev"
Requires-Dist: twine>=5; extra == "dev"
Dynamic: license-file
